Workbook

Sheet Setup
A1: HER JOURNEY 240 — PERSONAL SETUP & CALORIE CALCULATOR
A2: SECTION 1: HER PROFILE
A3: Full Name | B3: Deep | C3: Editable in app settings
A4: Age | B4: 25 | C4: Years
A5: Sex | B5: Female | C5: Used in Mifflin-St Jeor formula
A6: Current Weight (kg) | B6: 86.2 | C6: Latest check-in weight
A7: Baseline Starting Weight (kg) | B7: 88.5 | C7: October 24, 2026 baseline
A8: Height (cm) | B8: 158 | C8: Approx 5'2" (Ask to confirm in settings)
A9: Location | B9: Bengaluru, Karnataka, India | C9: Bengaluru, Karnataka, India
A10: Food Preference | B10: Non-vegetarian (with vegetarian alternatives) | C10: Home-cooked South Indian + chicken, egg, veg alts
A11: Exercise Preference | B11: Joyful beginner Zumba dance & comfortable walking (no gym/weightlifting routine) | C11: Joyful beginner Zumba YouTube sessions & walking
A12: Plan Start Date | B12: 2026-10-24 | C12: October 24, 2026 (Day 1)
A13: Plan End Date | B13: 2027-06-20 | C13: June 20, 2027 (Day 240)
A14: Total Journey Days | B14: 240 | C14: Inclusive calendar days
A16: SECTION 2: ENERGY & CALORIE CALCULATOR
A17: Mifflin-St Jeor BMR (kcal) | B17: =ROUND(10*B5 + 6.25*B7 - 5*B3 - 161, 1) | C17: Female BMR formula: 10*W + 6.25*H - 5*Age - 161 | D17: 1563.5 kcal
A18: Baseline Activity Multiplier | B18: 1.2 | C18: Sedentary baseline: desk work & daily life (Zumba logged separately) | D18: 1.20
A19: Baseline Maintenance TDEE (kcal) | B19: =ROUND(B16*B17, 1) | C19: Baseline daily expenditure before separately logged workouts | D19: 1876.2 kcal
A20: Planned Moderate Calorie Deficit (kcal) | B20: 350 | C20: Gentle, non-aggressive sustainable deficit (no starvation) | D20: 350 kcal
A21: Planned Daily Calorie Target (kcal) | B21: =ROUND(B18 - B19, 0) | C21: Planned daily food calorie intake | D21: 1526 kcal
A22: Planned Daily Protein Target (g) | B22: 85 | C22: Optimal muscle support (~1.0 g/kg) | D22: 85 g
A23: Planned Daily Carbohydrates (g) | B23: 175 | C23: Complex grains: millet, oats, rice, atta | D23: 175 g
A24: Planned Daily Fat (g) | B24: 42 | C24: Nourishing fats: eggs, curd, seeds, light ghee | D24: 42 g
A25: Estimated Daily Meal Cost (INR) | B25: ₹150 - ₹210 | C25: Affordable Bengaluru grocery budget | D25: ₹150 - ₹210
A27: SECTION 3: SCIENTIFIC METHODOLOGY & PRIVACY DISCLAIMERS
A28: Energy Model Rule 1 | B28: Baseline expenditure excludes exercise. Separately logged Zumba & walking calories are added to calculate TDEE.
A29: Energy Model Rule 2 | B29: Deficit = TDEE - Actual Calories Consumed. Positive = Deficit; Negative = Surplus.
A30: Weight Fluctuation Note | B30: Single-day weigh-ins fluctuate due to menstrual cycle, water retention, and sodium. Never interpret 1-day change as fat gain.
A31: Rest Day Rule | B31: REST MEANS REST. On rest days, 0 workout calories required, no mandatory cardio or dance, no pressure.
A32: Medical Disclaimer | B32: All calculations are estimates for educational wellness support, not medical diagnoses or guaranteed fat loss.

Sheet Daily Diet Plan
A1: Date | B1: Day # | C1: Day of Week | D1: Menu Theme | E1: Breakfast Option 1 (Recommended) | F1: Breakfast Option 2 (Alt) | G1: Breakfast Option 3 (Veg Alt) | H1: Mid-Morning Refresher / Snack | I1: Lunch Option 1 (Non-Veg) | J1: Lunch Option 2 (Egg/Fish) | K1: Lunch Option 3 (Veg / Paneer) | L1: Evening Snack & Crunch | M1: Dinner Option 1 (High Protein) | N1: Dinner Option 2 (Veg Bhurji/Paneer) | O1: Dinner Option 3 (Light Khichdi/Soup) | P1: Pre / Post Workout Option | Q1: Planned Cals (kcal) | R1: Planned Protein (g) | S1: Planned Carbs (g) | T1: Planned Fat (g) | U1: Estimated Cost (₹) | V1: Cooking & Kitchen Scale Notes
A2: 2026-10-24 | B2: 1 | C2: Saturday | D2: Comfort Steamed Staples & Bengaluru Chicken Curry | E2: Steamed Idlis (3 pcs, 110g) + Veg Sambar (150ml) + 2 Boiled Eggs (100g) [340 kcal, 19g P, 38g C, 12g F, ₹35] | F2: Steamed Idlis (3 pcs) + Veg Sambar + 1 cup warm sprouted moong salad (100g) [310 kcal, 13g P, 46g C, 5g F, ₹25] | G2: Ragi Dosa (2 medium, 120g) + Mint Chutney (30g) + 1 Boiled Egg [320 kcal, 14g P, 42g C, 11g F, ₹28] | H2: Tender Coconut Water (220ml) + Handful Roasted Chana (25g) [130 kcal, 5g P, 22g C, 2g F, ₹40] | Alt: Fresh Papaya slices (150g) + 5 soaked almonds [110 kcal, 3g P, 22g C, 3g F, ₹30] | I2: Sona Masoori Rice (150g cooked / 55g raw) + Bengaluru Chicken Curry (130g raw / 95g cooked meat) + French Beans Palya (130g) + Pepper Rasam [475 kcal, 34g P, 48g C, 14g F, ₹75] | J2: 2 Soft Wheat Phulkas (80g) + Homestyle Egg Curry (2 eggs in onion-tomato gravy) + Cabbage Poriyal (140g) [440 kcal, 21g P, 48g C, 16g F, ₹40] | K2: Sona Masoori Rice (150g) + Thick Toor Dal Tadka (180g) + Paneer Palya (80g paneer) + Fresh Curd (100g) [480 kcal, 23g P, 54g C, 18g F, ₹55] | L2: Spiced Boiled Sundal / Chickpeas (80g) with mustard tempering & lemon [140 kcal, 7g P, 22g C, 3g F, ₹20] | Alt: Roasted Makhana (30g) in 1/2 tsp ghee & rock salt [130 kcal, 3g P, 21g C, 3.5g F, ₹25] | M2: 2 Soft Whole Wheat Phulkas (75g) + Grilled/Pan Chicken Curry (100g meat) + Cucumber Tomato Salad (120g) [420 kcal, 31g P, 42g C, 12g F, ₹65] | N2: 2 Phulkas (75g) + Fresh Paneer Bhurji (90g paneer with capsicum & onion) + Tomato Clear Soup [440 kcal, 20g P, 42g C, 20g F, ₹55] | O2: Warm Rice-Moong Dal Khichdi (220g) + Fresh Curd (100g) + Steamed Beetroot Poriyal (100g) [380 kcal, 14g P, 58g C, 8g F, ₹35] | P2: Optional Pre: 1 small banana (80g) [70 kcal] • Post: 1 glass warm toned milk with turmeric (180ml) [95 kcal, 6g P] | Q2: 1505 | R2: 96 | S2: 172 | T2: 43 | U2: 235 | V2: Steam idlis in idli cooker for 10-12 mins. Weigh 110g cooked on kitchen scale. Zero plate on scale, measure 150g warm rice, then add 95g cooked chicken meat without bones.
A3: 2026-10-25 | B3: 2 | C3: Sunday | D3: Iron-Rich Poha, Egg Curry & Golden Turmeric Phulkas | E3: Vegetable Poha (160g cooked) tempered with mustard & roasted peanuts (15g) + 1 Boiled Egg [330 kcal, 13g P, 44g C, 11g F, ₹28] | F3: Vegetable Poha (180g) + 1 glass warm toned milk (150ml) [310 kcal, 11g P, 48g C, 8g F, ₹24] | G3: Rolled Oats cooked in milk (40g oats + 180ml toned milk) with half diced apple [290 kcal, 12g P, 45g C, 6g F, ₹30] | H3: Spiced Majjige / Buttermilk (220ml) with grated ginger & curry leaves [45 kcal, 3g P, 4g C, 1.5g F, ₹15] | Alt: 1 Crisp Guava or Apple (130g) with pinch of rock salt [75 kcal, 1.5g P, 18g C, 0.5g F, ₹20] | I3: 2 Soft Phulkas (80g) + 2 Boiled Eggs in Onion-Tomato Gravy (120g gravy) + Ridge Gourd (Heerekayi) Palya (140g) [450 kcal, 22g P, 48g C, 17g F, ₹45] | J3: Sona Masoori Rice (150g) + Fish Curry (120g rohu/pomfret in light coconut gravy) + Beans Poriyal (120g) [460 kcal, 32g P, 46g C, 13g F, ₹80] | K3: Cooked Rice (150g) + Mixed Vegetable Sambar (180g) + Pan-seared Tofu or Paneer (80g) + Cucumber Slices [465 kcal, 21g P, 52g C, 17g F, ₹55] | L3: Boiled Sweet Corn (120g) with lemon squeeze & chaat masala [120 kcal, 4g P, 24g C, 1.5g F, ₹20] | Alt: Roasted Kadale / Chana (30g) + Warm Elaichi Green Tea [125 kcal, 6g P, 18g C, 2.5g F, ₹15] | M3: 2 Soft Phulkas (75g) + Fresh Paneer Bhurji (90g paneer, capsicum, tomato) + Warm Tomato Rasam (150ml) [445 kcal, 21g P, 44g C, 19g F, ₹60] | N3: 2 Ragi Rotis (130g) + Chicken Curry (90g cooked meat) + Onion Cucumber Raita (80g) [430 kcal, 30g P, 46g C, 11g F, ₹70] | O3: Moong Dal Vegetable Dalia Khichdi (220g) + Fresh Curd (100g) [390 kcal, 16g P, 54g C, 9g F, ₹35] | P3: Optional Pre: 2 Medjool dates [80 kcal] • Post: 1 boiled egg white or 100g warm milk [55 kcal, 4g P] | Q3: 1390 | R3: 63 | S3: 164 | T3: 50 | U3: 168 | V3: Rinse thick poha in colander, drain well. Sauté with onion, curry leaves, carrots & roasted peanuts. Prick boiled eggs gently before simmering in gravy to absorb rich flavours.
A4: 2026-10-26 | B4: 3 | C4: Monday | D4: Bengaluru Rava Upma & Fresh Coastal Home Curry | E4: Bengaluru Vegetable Rava Upma (180g cooked) with roasted peanuts + 1 Boiled Egg [340 kcal, 14g P, 44g C, 12g F, ₹26] | F4: Vegetable Upma (180g) + 1 glass warm toned milk (150ml) [320 kcal, 11g P, 48g C, 9g F, ₹24] | G4: Steamed Idlis (3 pcs) with Mint Toor Dal Chutney (40g) + 1 Boiled Egg [320 kcal, 15g P, 42g C, 9g F, ₹28] | H4: Fresh Fruit Bowl (150g watermelon or papaya) + 6 soaked almonds [110 kcal, 3g P, 22g C, 3g F, ₹30] | Alt: Tender Coconut Water (220ml) [45 kcal, 1g P, 10g C, 0g F, ₹35] | I4: Sona Masoori Rice (150g cooked) + Bengaluru Fish Curry (120g fresh fish in light gravy) + Cabbage & Pea Poriyal (130g) + Rasam [450 kcal, 33g P, 46g C, 13g F, ₹80] | J4: 2 Phulkas (80g) + Chicken Curry (95g cooked meat) + Cucumber Carrot Salad (100g) [440 kcal, 31g P, 44g C, 13g F, ₹65] | K4: Rice (150g) + Thick Chana Dal (180g) + Beans Palya (130g) + Fresh Curd (100g) [470 kcal, 22g P, 56g C, 15g F, ₹45] | L4: Roasted Puri Kadale / Chana (30g) + Warm Ginger Tea (100ml low-fat milk) [140 kcal, 6g P, 20g C, 3.5g F, ₹18] | Alt: Spiced Boiled Moong Sprouts (80g) with lime & salt [110 kcal, 7g P, 18g C, 1g F, ₹15] | M4: 2 Soft Phulkas (75g) + Soya Chunks & Green Pea Curry (45g dry soya + 50g peas) + Fresh Curd (80g) [420 kcal, 29g P, 48g C, 9g F, ₹40] | N4: 2 Phulkas (75g) + 2 Boiled Eggs in Homestyle Curry (100g) + Sliced Cucumber [410 kcal, 21g P, 42g C, 15g F, ₹38] | O4: 2 Ragi Rotis (120g) + Mixed Vegetable Sambar (180ml) + Sautéed Palak (100g) [380 kcal, 14g P, 54g C, 8g F, ₹30] | P4: Optional Pre: 1 cup tender coconut water [45 kcal] • Post: 1 glass warm milk (150ml) [85 kcal, 5g P] | Q4: 1460 | R4: 85 | S4: 180 | T4: 40.5 | U4: 194 | V4: Dry roast semolina lightly. Tempered with mustard seeds, chana dal, green chillies & mixed veggies. Use fresh local fish cuts (rohu, pomfret, or seer fish). Simmer gently for 8 mins.
A5: 2026-10-27 | B5: 4 | C5: Tuesday | D5: Nourishing Rolled Oats & Tender Chicken Palya | E5: Warm Rolled Oats (40g dry + 180ml toned milk) + 1 Boiled Egg + Apple slices (50g) [345 kcal, 18g P, 46g C, 10g F, ₹35] | F5: Vegetable Poha (160g cooked) + 2 Boiled Eggs [360 kcal, 18g P, 42g C, 14g F, ₹32] | G5: 2 Plain Dosas (120g) + Toor Dal Sambar (150ml) + 1 cup warm sprouted moong [330 kcal, 14g P, 48g C, 7g F, ₹25] | H5: Tender Coconut Water (220ml) + 5 Soaked Almonds [95 kcal, 3g P, 12g C, 4g F, ₹40] | Alt: Fresh Spiced Buttermilk (220ml) with coriander & rock salt [45 kcal, 3g P, 4g C, 1.5g F, ₹15] | I5: Sona Masoori Rice (150g cooked) + Tender Chicken Curry (130g raw / 95g meat) + Palak (Spinach) Palya (140g) + Rasam [470 kcal, 35g P, 46g C, 13g F, ₹75] | J5: 2 Soft Phulkas (80g) + Fresh Paneer Curry (85g paneer in light gravy) + French Beans Palya (120g) [450 kcal, 21g P, 44g C, 19g F, ₹55] | K5: Rice (150g) + Toor Dal Tadka (180g) + 2 Boiled Eggs + Beetroot Poriyal (120g) [460 kcal, 25g P, 52g C, 14g F, ₹42] | L5: Roasted Makhana (30g) + Hot Green Tea with lemon [130 kcal, 3g P, 21g C, 3.5g F, ₹25] | Alt: Boiled Chickpeas Sundal (70g) with mustard & curry leaves [125 kcal, 6g P, 20g C, 2.5g F, ₹18] | M5: 2 Soft Phulkas (75g) + 2 Boiled Eggs in Tomato Onion Curry + Cucumber Salad (100g) [415 kcal, 21g P, 42g C, 15g F, ₹38] | N5: 2 Phulkas (75g) + Grilled Chicken Strips (100g cooked) + Mixed Sautéed Capsicum & Onions [425 kcal, 32g P, 40g C, 11g F, ₹65] | O5: Warm Moong Dal Vegetable Khichdi (220g) + Fresh Curd (100g) [380 kcal, 15g P, 56g C, 8g F, ₹35] | P5: Optional Pre: 1 small banana [70 kcal] • Post: 1 cup warm turmeric milk [90 kcal, 6g P] | Q5: 1455 | R5: 80 | S5: 167 | T5: 45.5 | U5: 213 | V5: Cook oats in milk for 4 mins on medium flame. Stir in pinch of cinnamon powder. Weigh raw boneless chicken (130g). Steam spinach lightly with mustard tempering.
A6: 2026-10-28 | B6: 5 | C6: Wednesday | D6: Calcium-Rich Ragi Dosa & Fresh Country Egg Feast | E6: Ragi Dosa (2 medium, 120g) + Coconut Mint Chutney (30g) + 2 Boiled Eggs [350 kcal, 19g P, 40g C, 13g F, ₹35] | F6: Steamed Idlis (3 pcs, 110g) + Vegetable Sambar (150ml) + 1 Boiled Egg [310 kcal, 13g P, 44g C, 8g F, ₹25] | G6: Vegetable Upma (180g) + Warm Toned Milk (150ml) [320 kcal, 11g P, 48g C, 9g F, ₹22] | H6: Fresh Seasonal Fruit (1 Medium Apple or 150g Papaya) + 6 Almonds [115 kcal, 3g P, 22g C, 3.5g F, ₹30] | Alt: Tender Coconut Water (220ml) [45 kcal, 1g P, 10g C, 0g F, ₹35] | I6: 2 Soft Phulkas (80g) + Homestyle Egg Curry (2 eggs) + Cabbage & Carrot Poriyal (140g) + Rasam [445 kcal, 22g P, 48g C, 16g F, ₹42] | J6: Sona Masoori Rice (150g) + Bengaluru Chicken Curry (95g meat) + Beans Palya (120g) [475 kcal, 34g P, 48g C, 14g F, ₹75] | K6: Rice (150g) + Thick Toor Dal Tadka (180g) + Fresh Curd (100g) + Tomato Cucumber Salad [440 kcal, 18g P, 56g C, 14g F, ₹40] | L6: Spiced Boiled Sundal / Chickpeas (80g) with lime [140 kcal, 7g P, 22g C, 3g F, ₹20] | Alt: Roasted Makhana (30g) in 1/2 tsp ghee & rock salt [130 kcal, 3g P, 21g C, 3.5g F, ₹25] | M6: 2 Soft Phulkas (75g) + Home Chicken Curry (100g meat) + Cucumber Salad (100g) [420 kcal, 31g P, 42g C, 12g F, ₹65] | N6: 2 Phulkas (75g) + Fresh Paneer Bhurji (90g paneer, capsicum, onion) + Clear Soup [440 kcal, 20g P, 42g C, 20g F, ₹55] | O6: Rice-Moong Dal Khichdi (220g) + Curd (100g) + Lauki Sabzi (120g) [385 kcal, 14g P, 58g C, 8.5g F, ₹35] | P6: Optional Pre: 1 cup tender coconut water [45 kcal] • Post: 1 glass warm milk (150ml) [85 kcal, 5g P] | Q6: 1470 | R6: 82 | S6: 174 | T6: 47.5 | U6: 192 | V6: Mix ragi flour with equal water, pinch of salt, cumin seeds & chopped onion. Pour on medium hot tawa. Cook vegetables in minimum oil with mustard seeds, curry leaves & grated fresh coconut.
A7: 2026-10-29 | B7: 6 | C7: Thursday | D7: High-Fiber Soya Chunks & Comfort Idli Sambar | E7: Steamed Idlis (3 pcs, 110g) + Vegetable Sambar (150ml) + 2 Boiled Eggs [340 kcal, 19g P, 38g C, 12g F, ₹35] | F7: Vegetable Poha (160g cooked) + 1 Boiled Egg [310 kcal, 12g P, 44g C, 9g F, ₹26] | G7: Rolled Oats cooked in toned milk (40g + 180ml milk) with 1/2 apple [290 kcal, 12g P, 45g C, 6g F, ₹30] | H7: Spiced Buttermilk / Majjige (220ml) with curry leaves & ginger [45 kcal, 3g P, 4g C, 1.5g F, ₹15] | Alt: Fresh Papaya slices (150g) + 5 almonds [110 kcal, 3g P, 22g C, 3g F, ₹28] | I7: Sona Masoori Rice (150g cooked) + Soya Chunks Curry (45g dry soya chunks cooked in onion-tomato gravy) + French Beans Palya (130g) + Rasam [460 kcal, 31g P, 56g C, 9g F, ₹42] | J7: 2 Phulkas (80g) + Chicken Curry (95g meat) + Cabbage Poriyal (120g) [440 kcal, 31g P, 44g C, 13g F, ₹65] | K7: Rice (150g) + Thick Toor Dal (180g) + 2 Boiled Eggs + Ridge Gourd Palya (120g) [455 kcal, 24g P, 52g C, 14g F, ₹40] | L7: Roasted Kadale / Chana (30g) + Hot Elaichi Tea (100ml milk) [140 kcal, 6g P, 20g C, 3.5g F, ₹18] | Alt: Roasted Makhana (30g) in ghee & rock salt [130 kcal, 3g P, 21g C, 3.5g F, ₹25] | M7: 2 Soft Phulkas (75g) + 2 Boiled Eggs in Mild Curry + Cucumber Carrot Salad (120g) [415 kcal, 21g P, 42g C, 15g F, ₹38] | N7: 2 Phulkas (75g) + Paneer Bhurji (90g paneer, capsicum, tomato) + Warm Soup [445 kcal, 20g P, 44g C, 19g F, ₹58] | O7: 2 Ragi Rotis (120g) + Chicken Curry (90g meat) + Cucumber Slices [425 kcal, 30g P, 46g C, 11g F, ₹68] | P7: Optional Pre: 1 small banana [70 kcal] • Post: 1 glass warm milk [90 kcal, 6g P] | Q7: 1400 | R7: 80 | S7: 160 | T7: 41 | U7: 151 | V7: Dip idlis in piping hot sambar. Eggs provide complete amino acid profile. Soak soya chunks in warm water for 15 mins. Squeeze out bitter water completely before cooking.
A8: 2026-10-30 | B8: 7 | C8: Friday | D8: Comfort Steamed Staples & Bengaluru Chicken Curry | E8: Steamed Idlis (3 pcs, 110g) + Veg Sambar (150ml) + 2 Boiled Eggs (100g) [340 kcal, 19g P, 38g C, 12g F, ₹35] | F8: Steamed Idlis (3 pcs) + Veg Sambar + 1 cup warm sprouted moong salad (100g) [310 kcal, 13g P, 46g C, 5g F, ₹25] | G8: Ragi Dosa (2 medium, 120g) + Mint Chutney (30g) + 1 Boiled Egg [320 kcal, 14g P, 42g C, 11g F, ₹28] | H8: Tender Coconut Water (220ml) + Handful Roasted Chana (25g) [130 kcal, 5g P, 22g C, 2g F, ₹40] | Alt: Fresh Papaya slices (150g) + 5 soaked almonds [110 kcal, 3g P, 22g C, 3g F, ₹30] | I8: Sona Masoori Rice (150g cooked / 55g raw) + Bengaluru Chicken Curry (130g raw / 95g cooked meat) + French Beans Palya (130g) + Pepper Rasam [475 kcal, 34g P, 48g C, 14g F, ₹75] | J8: 2 Soft Wheat Phulkas (80g) + Homestyle Egg Curry (2 eggs in onion-tomato gravy) + Cabbage Poriyal (140g) [440 kcal, 21g P, 48g C, 16g F, ₹40] | K8: Sona Masoori Rice (150g) + Thick Toor Dal Tadka (180g) + Paneer Palya (80g paneer) + Fresh Curd (100g) [480 kcal, 23g P, 54g C, 18g F, ₹55] | L8: Spiced Boiled Sundal / Chickpeas (80g) with mustard tempering & lemon [140 kcal, 7g P, 22g C, 3g F, ₹20] | Alt: Roasted Makhana (30g) in 1/2 tsp ghee & rock salt [130 kcal, 3g P, 21g C, 3.5g F, ₹25] | M8: 2 Soft Whole Wheat Phulkas (75g) + Grilled/Pan Chicken Curry (100g meat) + Cucumber Tomato Salad (120g) [420 kcal, 31g P, 42g C, 12g F, ₹65] | N8: 2 Phulkas (75g) + Fresh Paneer Bhurji (90g paneer with capsicum & onion) + Tomato Clear Soup [440 kcal, 20g P, 42g C, 20g F, ₹55] | O8: Warm Rice-Moong Dal Khichdi (220g) + Fresh Curd (100g) + Steamed Beetroot Poriyal (100g) [380 kcal, 14g P, 58g C, 8g F, ₹35] | P8: Optional Pre: 1 small banana (80g) [70 kcal] • Post: 1 glass warm toned milk with turmeric (180ml) [95 kcal, 6g P] | Q8: 1505 | R8: 96 | S8: 172 | T8: 43 | U8: 235 | V8: Steam idlis in idli cooker for 10-12 mins. Weigh 110g cooked on kitchen scale. Zero plate on scale, measure 150g warm rice, then add 95g cooked chicken meat without bones.
A9: 2026-10-31 | B9: 8 | C9: Saturday | D9: Iron-Rich Poha, Egg Curry & Golden Turmeric Phulkas | E9: Vegetable Poha (160g cooked) tempered with mustard & roasted peanuts (15g) + 1 Boiled Egg [330 kcal, 13g P, 44g C, 11g F, ₹28] | F9: Vegetable Poha (180g) + 1 glass warm toned milk (150ml) [310 kcal, 11g P, 48g C, 8g F, ₹24] | G9: Rolled Oats cooked in milk (40g oats + 180ml toned milk) with half diced apple [290 kcal, 12g P, 45g C, 6g F, ₹30] | H9: Spiced Majjige / Buttermilk (220ml) with grated ginger & curry leaves [45 kcal, 3g P, 4g C, 1.5g F, ₹15] | Alt: 1 Crisp Guava or Apple (130g) with pinch of rock salt [75 kcal, 1.5g P, 18g C, 0.5g F, ₹20] | I9: 2 Soft Phulkas (80g) + 2 Boiled Eggs in Onion-Tomato Gravy (120g gravy) + Ridge Gourd (Heerekayi) Palya (140g) [450 kcal, 22g P, 48g C, 17g F, ₹45] | J9: Sona Masoori Rice (150g) + Fish Curry (120g rohu/pomfret in light coconut gravy) + Beans Poriyal (120g) [460 kcal, 32g P, 46g C, 13g F, ₹80] | K9: Cooked Rice (150g) + Mixed Vegetable Sambar (180g) + Pan-seared Tofu or Paneer (80g) + Cucumber Slices [465 kcal, 21g P, 52g C, 17g F, ₹55] | L9: Boiled Sweet Corn (120g) with lemon squeeze & chaat masala [120 kcal, 4g P, 24g C, 1.5g F, ₹20] | Alt: Roasted Kadale / Chana (30g) + Warm Elaichi Green Tea [125 kcal, 6g P, 18g C, 2.5g F, ₹15] | M9: 2 Soft Phulkas (75g) + Fresh Paneer Bhurji (90g paneer, capsicum, tomato) + Warm Tomato Rasam (150ml) [445 kcal, 21g P, 44g C, 19g F, ₹60] | N9: 2 Ragi Rotis (130g) + Chicken Curry (90g cooked meat) + Onion Cucumber Raita (80g) [430 kcal, 30g P, 46g C, 11g F, ₹70] | O9: Moong Dal Vegetable Dalia Khichdi (220g) + Fresh Curd (100g) [390 kcal, 16g P, 54g C, 9g F, ₹35] | P9: Optional Pre: 2 Medjool dates [80 kcal] • Post: 1 boiled egg white or 100g warm milk [55 kcal, 4g P] | Q9: 1390 | R9: 63 | S9: 164 | T9: 50 | U9: 168 | V9: Rinse thick poha in colander, drain well. Sauté with onion, curry leaves, carrots & roasted peanuts. Prick boiled eggs gently before simmering in gravy to absorb rich flavours.
A10: 2026-11-01 | B10: 9 | C10: Sunday | D10: Bengaluru Rava Upma & Fresh Coastal Home Curry | E10: Bengaluru Vegetable Rava Upma (180g cooked) with roasted peanuts + 1 Boiled Egg [340 kcal, 14g P, 44g C, 12g F, ₹26] | F10: Vegetable Upma (180g) + 1 glass warm toned milk (150ml) [320 kcal, 11g P, 48g C, 9g F, ₹24] | G10: Steamed Idlis (3 pcs) with Mint Toor Dal Chutney (40g) + 1 Boiled Egg [320 kcal, 15g P, 42g C, 9g F, ₹28] | H10: Fresh Fruit Bowl (150g watermelon or papaya) + 6 soaked almonds [110 kcal, 3g P, 22g C, 3g F, ₹30] | Alt: Tender Coconut Water (220ml) [45 kcal, 1g P, 10g C, 0g F, ₹35] | I10: Sona Masoori Rice (150g cooked) + Bengaluru Fish Curry (120g fresh fish in light gravy) + Cabbage & Pea Poriyal (130g) + Rasam [450 kcal, 33g P, 46g C, 13g F, ₹80] | J10: 2 Phulkas (80g) + Chicken Curry (95g cooked meat) + Cucumber Carrot Salad (100g) [440 kcal, 31g P, 44g C, 13g F, ₹65] | K10: Rice (150g) + Thick Chana Dal (180g) + Beans Palya (130g) + Fresh Curd (100g) [470 kcal, 22g P, 56g C, 15g F, ₹45] | L10: Roasted Puri Kadale / Chana (30g) + Warm Ginger Tea (100ml low-fat milk) [140 kcal, 6g P, 20g C, 3.5g F, ₹18] | Alt: Spiced Boiled Moong Sprouts (80g) with lime & salt [110 kcal, 7g P, 18g C, 1g F, ₹15] | M10: 2 Soft Phulkas (75g) + Soya Chunks & Green Pea Curry (45g dry soya + 50g peas) + Fresh Curd (80g) [420 kcal, 29g P, 48g C, 9g F, ₹40] | N10: 2 Phulkas (75g) + 2 Boiled Eggs in Homestyle Curry (100g) + Sliced Cucumber [410 kcal, 21g P, 42g C, 15g F, ₹38] | O10: 2 Ragi Rotis (120g) + Mixed Vegetable Sambar (180ml) + Sautéed Palak (100g) [380 kcal, 14g P, 54g C, 8g F, ₹30] | P10: Optional Pre: 1 cup tender coconut water [45 kcal] • Post: 1 glass warm milk (150ml) [85 kcal, 5g P] | Q10: 1460 | R10: 85 | S10: 180 | T10: 40.5 | U10: 194 | V10: Dry roast semolina lightly. Tempered with mustard seeds, chana dal, green chillies & mixed veggies. Use fresh local fish cuts (rohu, pomfret, or seer fish). Simmer gently for 8 mins.
A11: 2026-11-02 | B11: 10 | C11: Monday | D11: Nourishing Rolled Oats & Tender Chicken Palya | E11: Warm Rolled Oats (40g dry + 180ml toned milk) + 1 Boiled Egg + Apple slices (50g) [345 kcal, 18g P, 46g C, 10g F, ₹35] | F11: Vegetable Poha (160g cooked) + 2 Boiled Eggs [360 kcal, 18g P, 42g C, 14g F, ₹32] | G11: 2 Plain Dosas (120g) + Toor Dal Sambar (150ml) + 1 cup warm sprouted moong [330 kcal, 14g P, 48g C, 7g F, ₹25] | H11: Tender Coconut Water (220ml) + 5 Soaked Almonds [95 kcal, 3g P, 12g C, 4g F, ₹40] | Alt: Fresh Spiced Buttermilk (220ml) with coriander & rock salt [45 kcal, 3g P, 4g C, 1.5g F, ₹15] | I11: Sona Masoori Rice (150g cooked) + Tender Chicken Curry (130g raw / 95g meat) + Palak (Spinach) Palya (140g) + Rasam [470 kcal, 35g P, 46g C, 13g F, ₹75] | J11: 2 Soft Phulkas (80g) + Fresh Paneer Curry (85g paneer in light gravy) + French Beans Palya (120g) [450 kcal, 21g P, 44g C, 19g F, ₹55] | K11: Rice (150g) + Toor Dal Tadka (180g) + 2 Boiled Eggs + Beetroot Poriyal (120g) [460 kcal, 25g P, 52g C, 14g F, ₹42] | L11: Roasted Makhana (30g) + Hot Green Tea with lemon [130 kcal, 3g P, 21g C, 3.5g F, ₹25] | Alt: Boiled Chickpeas Sundal (70g) with mustard & curry leaves [125 kcal, 6g P, 20g C, 2.5g F, ₹18] | M11: 2 Soft Phulkas (75g) + 2 Boiled Eggs in Tomato Onion Curry + Cucumber Salad (100g) [415 kcal, 21g P, 42g C, 15g F, ₹38] | N11: 2 Phulkas (75g) + Grilled Chicken Strips (100g cooked) + Mixed Sautéed Capsicum & Onions [425 kcal, 32g P, 40g C, 11g F, ₹65] | O11: Warm Moong Dal Vegetable Khichdi (220g) + Fresh Curd (100g) [380 kcal, 15g P, 56g C, 8g F, ₹35] | P11: Optional Pre: 1 small banana [70 kcal] • Post: 1 cup warm turmeric milk [90 kcal, 6g P] | Q11: 1455 | R11: 80 | S11: 167 | T11: 45.5 | U11: 213 | V11: Cook oats in milk for 4 mins on medium flame. Stir in pinch of cinnamon powder. Weigh raw boneless chicken (130g). Steam spinach lightly with mustard tempering.
A12: 2026-11-03 | B12: 11 | C12: Tuesday | D12: Calcium-Rich Ragi Dosa & Fresh Country Egg Feast | E12: Ragi Dosa (2 medium, 120g) + Coconut Mint Chutney (30g) + 2 Boiled Eggs [350 kcal, 19g P, 40g C, 13g F, ₹35] | F12: Steamed Idlis (3 pcs, 110g) + Vegetable Sambar (150ml) + 1 Boiled Egg [310 kcal, 13g P, 44g C, 8g F, ₹25] | G12: Vegetable Upma (180g) + Warm Toned Milk (150ml) [320 kcal, 11g P, 48g C, 9g F, ₹22] | H12: Fresh Seasonal Fruit (1 Medium Apple or 150g Papaya) + 6 Almonds [115 kcal, 3g P, 22g C, 3.5g F, ₹30] | Alt: Tender Coconut Water (220ml) [45 kcal, 1g P, 10g C, 0g F, ₹35] | I12: 2 Soft Phulkas (80g) + Homestyle Egg Curry (2 eggs) + Cabbage & Carrot Poriyal (140g) + Rasam [445 kcal, 22g P, 48g C, 16g F, ₹42] | J12: Sona Masoori Rice (150g) + Bengaluru Chicken Curry (95g meat) + Beans Palya (120g) [475 kcal, 34g P, 48g C, 14g F, ₹75] | K12: Rice (150g) + Thick Toor Dal Tadka (180g) + Fresh Curd (100g) + Tomato Cucumber Salad [440 kcal, 18g P, 56g C, 14g F, ₹40] | L12: Spiced Boiled Sundal / Chickpeas (80g) with lime [140 kcal, 7g P, 22g C, 3g F, ₹20] | Alt: Roasted Makhana (30g) in 1/2 tsp ghee & rock salt [130 kcal, 3g P, 21g C, 3.5g F, ₹25] | M12: 2 Soft Phulkas (75g) + Home Chicken Curry (100g meat) + Cucumber Salad (100g) [420 kcal, 31g P, 42g C, 12g F, ₹65] | N12: 2 Phulkas (75g) + Fresh Paneer Bhurji (90g paneer, capsicum, onion) + Clear Soup [440 kcal, 20g P, 42g C, 20g F, ₹55] | O12: Rice-Moong Dal Khichdi (220g) + Curd (100g) + Lauki Sabzi (120g) [385 kcal, 14g P, 58g C, 8.5g F, ₹35] | P12: Optional Pre: 1 cup tender coconut water [45 kcal] • Post: 1 glass warm milk (150ml) [85 kcal, 5g P] | Q12: 1470 | R12: 82 | S12: 174 | T12: 47.5 | U12: 192 | V12: Mix ragi flour with equal water, pinch of salt, cumin seeds & chopped onion. Pour on medium hot tawa. Cook vegetables in minimum oil with mustard seeds, curry leaves & grated fresh coconut.
A13: 2026-11-04 | B13: 12 | C13: Wednesday | D13: High-Fiber Soya Chunks & Comfort Idli Sambar | E13: Steamed Idlis (3 pcs, 110g) + Vegetable Sambar (150ml) + 2 Boiled Eggs [340 kcal, 19g P, 38g C, 12g F, ₹35] | F13: Vegetable Poha (160g cooked) + 1 Boiled Egg [310 kcal, 12g P, 44g C, 9g F, ₹26] | G13: Rolled Oats cooked in toned milk (40g + 180ml milk) with 1/2 apple [290 kcal, 12g P, 45g C, 6g F, ₹30] | H13: Spiced Buttermilk / Majjige (220ml) with curry leaves & ginger [45 kcal, 3g P, 4g C, 1.5g F, ₹15] | Alt: Fresh Papaya slices (150g) + 5 almonds [110 kcal, 3g P, 22g C, 3g F, ₹28] | I13: Sona Masoori Rice (150g cooked) + Soya Chunks Curry (45g dry soya chunks cooked in onion-tomato gravy) + French Beans Palya (130g) + Rasam [460 kcal, 31g P, 56g C, 9g F, ₹42] | J13: 2 Phulkas (80g) + Chicken Curry (95g meat) + Cabbage Poriyal (120g) [440 kcal, 31g P, 44g C, 13g F, ₹65] | K13: Rice (150g) + Thick Toor Dal (180g) + 2 Boiled Eggs + Ridge Gourd Palya (120g) [455 kcal, 24g P, 52g C, 14g F, ₹40] | L13: Roasted Kadale / Chana (30g) + Hot Elaichi Tea (100ml milk) [140 kcal, 6g P, 20g C, 3.5g F, ₹18] | Alt: Roasted Makhana (30g) in ghee & rock salt [130 kcal, 3g P, 21g C, 3.5g F, ₹25] | M13: 2 Soft Phulkas (75g) + 2 Boiled Eggs in Mild Curry + Cucumber Carrot Salad (120g) [415 kcal, 21g P, 42g C, 15g F, ₹38] | N13: 2 Phulkas (75g) + Paneer Bhurji (90g paneer, capsicum, tomato) + Warm Soup [445 kcal, 20g P, 44g C, 19g F, ₹58] | O13: 2 Ragi Rotis (120g) + Chicken Curry (90g meat) + Cucumber Slices [425 kcal, 30g P, 46g C, 11g F, ₹68] | P13: Optional Pre: 1 small banana [70 kcal] • Post: 1 glass warm milk [90 kcal, 6g P] | Q13: 1400 | R13: 80 | S13: 160 | T13: 41 | U13: 151 | V13: Dip idlis in piping hot sambar. Eggs provide complete amino acid profile. Soak soya chunks in warm water for 15 mins. Squeeze out bitter water completely before cooking.
... A241: 2027-06-20 | B241: 240 | C241: Sunday | D241: High-Fiber Soya Chunks & Comfort Idli Sambar | E241: Steamed Idlis (3 pcs, 110g) + Vegetable Sambar (150ml) + 2 Boiled Eggs [340 kcal, 19g P, 38g C, 12g F, ₹35] | F241: Vegetable Poha (160g cooked) + 1 Boiled Egg [310 kcal, 12g P, 44g C, 9g F, ₹26] | G241: Rolled Oats cooked in toned milk (40g + 180ml milk) with 1/2 apple [290 kcal, 12g P, 45g C, 6g F, ₹30] | H241: Spiced Buttermilk / Majjige (220ml) with curry leaves & ginger [45 kcal, 3g P, 4g C, 1.5g F, ₹15] | Alt: Fresh Papaya slices (150g) + 5 almonds [110 kcal, 3g P, 22g C, 3g F, ₹28] | I241: Sona Masoori Rice (150g cooked) + Soya Chunks Curry (45g dry soya chunks cooked in onion-tomato gravy) + French Beans Palya (130g) + Rasam [460 kcal, 31g P, 56g C, 9g F, ₹42] | J241: 2 Phulkas (80g) + Chicken Curry (95g meat) + Cabbage Poriyal (120g) [440 kcal, 31g P, 44g C, 13g F, ₹65] | K241: Rice (150g) + Thick Toor Dal (180g) + 2 Boiled Eggs + Ridge Gourd Palya (120g) [455 kcal, 24g P, 52g C, 14g F, ₹40] | L241: Roasted Kadale / Chana (30g) + Hot Elaichi Tea (100ml milk) [140 kcal, 6g P, 20g C, 3.5g F, ₹18] | Alt: Roasted Makhana (30g) in ghee & rock salt [130 kcal, 3g P, 21g C, 3.5g F, ₹25] | M241: 2 Soft Phulkas (75g) + 2 Boiled Eggs in Mild Curry + Cucumber Carrot Salad (120g) [415 kcal, 21g P, 42g C, 15g F, ₹38] | N241: 2 Phulkas (75g) + Paneer Bhurji (90g paneer, capsicum, tomato) + Warm Soup [445 kcal, 20g P, 44g C, 19g F, ₹58] | O241: 2 Ragi Rotis (120g) + Chicken Curry (90g meat) + Cucumber Slices [425 kcal, 30g P, 46g C, 11g F, ₹68] | P241: Optional Pre: 1 small banana [70 kcal] • Post: 1 glass warm milk [90 kcal, 6g P] | Q241: 1400 | R241: 80 | S241: 160 | T241: 41 | U241: 151 | V241: Dip idlis in piping hot sambar. Eggs provide complete amino acid profile. Soak soya chunks in warm water for 15 mins. Squeeze out bitter water completely before cooking.

Sheet Daily Zumba & Movement Plan
A1: Date | B1: Day # | C1: Day of Week | D1: Session Type | E1: Zumba Routine / Rest Title | F1: Duration (Mins) | G1: Estimated Burn (kcal) | H1: Dance Style | I1: Warm-up & Instructions | J1: Main Dance Steps / Flow | K1: Cool-down & Breathing | L1: Low-Impact / Chair Modifications | M1: Verified YouTube Zumba Link
A2: 2026-10-24 | B2: 1 | C2: Saturday | D2: REST DAY | E2: REST DAY — Rest, Recover & Nourish ❤️ | F2: 0 | G2: 0 | H2: Restorative Rest | I2: Day 1 of Journey & Period Care — Honoring your body with warm rest & gentle self-care ❤️ | J2: Zero workout assigned. Rest is 100% productive and honored. Keep hydration & comfortable meals. | K2: Hand on heart, deep peaceful breathing, soothing chamomile or warm water. | L2: Optional gentle stroll around room if desired, never mandatory. | M2: N/A (Scheduled Rest Day)
A3: 2026-10-25 | B3: 2 | C3: Sunday | D3: ZUMBA SESSION | E3: 12-Min Gentle Slow Dance & Pelvic Sway (Restorative Flow) | F3: 12 | G3: 55 | H3: Restorative Slow Dance | I3: 2 minutes deep belly breaths sitting or standing softly. Ultra-gentle soothing music. Slow hip sways that relieve pelvic tension, lower back stiffness, and cramps. | J3: Gentle Hip Sway (4 mins) • Slow Waltz Step (4 mins) • Supported Side Reach (4 mins) | K3: 3 minutes supported relaxation with warm water. | L3: 100% seated on a comfortable sofa or chair. | M3: https://www.youtube.com/results?search_query=10+minute+gentle+restorative+dance+and+stretch
A4: 2026-10-26 | B4: 3 | C4: Monday | D4: ZUMBA SESSION | E4: 15-Min Joyful Beginner Bollywood Zumba Dance Party | F4: 15 | G4: 105 | H4: Bollywood Dance Fitness | I4: 2 minutes of slow shoulder rolls, side-to-side step touches, and wrist circles. Put on upbeat music! Follow easy beginner dance steps with no jumping. Sway your hips, pump your arms, and have fun. Never worry about perfection — just keep moving and smiling! ❤️ | J4: Bollywood Bhangra Bounce (3 mins) • Salsa Side-to-Side Step (4 mins) • Merengue March & Arm Reaches (4 mins) • Cumbia Hip Sway (4 mins) | K4: 2 minutes of gentle salsa breathing, slow swaying, and deep belly breath. | L4: Seated dance moves on a chair with expressive arm rolls and seated foot taps. | M4: https://www.youtube.com/results?search_query=15+minute+beginner+bollywood+dance+workout+low+impact
A5: 2026-10-27 | B5: 4 | C5: Tuesday | D5: ZUMBA SESSION | E5: 15-Min Feel-Good Latin Zumba Party (Knee-Friendly, Low Impact) | F5: 15 | G5: 105 | H5: Latin Fiesta Dance | I5: 2 minutes easy hip circles and gentle arm sweeps. Gentle Latin rhythms (Merengue, Salsa, Bachata). Keep knees soft and absorb rhythm naturally. | J5: Merengue 6-Count March (4 mins) • Salsa Forward & Back Step (4 mins) • Reggaeton Gentle Bounce (3 mins) • Bachata Side Touch (4 mins) | K5: 3 minutes calm swaying and calf stretch. | L5: Chair-supported dance steps holding dining table or chair back. | M5: https://www.youtube.com/results?search_query=15+minute+easy+zumba+dance+workout+for+beginners+low+impact
A6: 2026-10-28 | B6: 5 | C6: Wednesday | D6: REST DAY | E6: REST DAY — Rest, Recover & Nourish ❤️ | F6: 0 | G6: 0 | H6: Restorative Rest | I6: Scheduled REST DAY (Wednesday) — Muscle recovery, sleep & nervous system rest. Zero workout pressure! ❤️ | J6: Zero workout assigned. Rest is 100% productive and honored. Keep hydration & comfortable meals. | K6: Hand on heart, deep peaceful breathing, soothing chamomile or warm water. | L6: Optional gentle stroll around room if desired, never mandatory. | M6: N/A (Scheduled Rest Day)
A7: 2026-10-29 | B7: 6 | C7: Thursday | D7: ZUMBA SESSION | E7: 15-Min Joyful Beginner Bollywood Zumba Dance Party | F7: 15 | G7: 105 | H7: Bollywood Dance Fitness | I7: 2 minutes of slow shoulder rolls, side-to-side step touches, and wrist circles. Put on upbeat music! Follow easy beginner dance steps with no jumping. Sway your hips, pump your arms, and have fun. Never worry about perfection — just keep moving and smiling! ❤️ | J7: Bollywood Bhangra Bounce (3 mins) • Salsa Side-to-Side Step (4 mins) • Merengue March & Arm Reaches (4 mins) • Cumbia Hip Sway (4 mins) | K7: 2 minutes of gentle salsa breathing, slow swaying, and deep belly breath. | L7: Seated dance moves on a chair with expressive arm rolls and seated foot taps. | M7: https://www.youtube.com/results?search_query=15+minute+beginner+bollywood+dance+workout+low+impact
A8: 2026-10-30 | B8: 7 | C8: Friday | D8: ZUMBA SESSION | E8: 15-Min Feel-Good Latin Zumba Party (Knee-Friendly, Low Impact) | F8: 15 | G8: 105 | H8: Latin Fiesta Dance | I8: 2 minutes easy hip circles and gentle arm sweeps. Gentle Latin rhythms (Merengue, Salsa, Bachata). Keep knees soft and absorb rhythm naturally. | J8: Merengue 6-Count March (4 mins) • Salsa Forward & Back Step (4 mins) • Reggaeton Gentle Bounce (3 mins) • Bachata Side Touch (4 mins) | K8: 3 minutes calm swaying and calf stretch. | L8: Chair-supported dance steps holding dining table or chair back. | M8: https://www.youtube.com/results?search_query=15+minute+easy+zumba+dance+workout+for+beginners+low+impact
A9: 2026-10-31 | B9: 8 | C9: Saturday | D9: REST DAY | E9: REST DAY — Rest, Recover & Nourish ❤️ | F9: 0 | G9: 0 | H9: Restorative Rest | I9: Scheduled REST DAY (Saturday) — Muscle recovery, sleep & nervous system rest. Zero workout pressure! ❤️ | J9: Zero workout assigned. Rest is 100% productive and honored. Keep hydration & comfortable meals. | K9: Hand on heart, deep peaceful breathing, soothing chamomile or warm water. | L9: Optional gentle stroll around room if desired, never mandatory. | M9: N/A (Scheduled Rest Day)
A10: 2026-11-01 | B10: 9 | C10: Sunday | D10: REST DAY | E10: REST DAY — Rest, Recover & Nourish ❤️ | F10: 0 | G10: 0 | H10: Restorative Rest | I10: Scheduled REST DAY (Sunday) — Muscle recovery, sleep & nervous system rest. Zero workout pressure! ❤️ | J10: Zero workout assigned. Rest is 100% productive and honored. Keep hydration & comfortable meals. | K10: Hand on heart, deep peaceful breathing, soothing chamomile or warm water. | L10: Optional gentle stroll around room if desired, never mandatory. | M10: N/A (Scheduled Rest Day)
A11: 2026-11-02 | B11: 10 | C11: Monday | D11: ZUMBA SESSION | E11: 15-Min Joyful Beginner Bollywood Zumba Dance Party | F11: 15 | G11: 105 | H11: Bollywood Dance Fitness | I11: 2 minutes of slow shoulder rolls, side-to-side step touches, and wrist circles. Put on upbeat music! Follow easy beginner dance steps with no jumping. Sway your hips, pump your arms, and have fun. Never worry about perfection — just keep moving and smiling! ❤️ | J11: Bollywood Bhangra Bounce (3 mins) • Salsa Side-to-Side Step (4 mins) • Merengue March & Arm Reaches (4 mins) • Cumbia Hip Sway (4 mins) | K11: 2 minutes of gentle salsa breathing, slow swaying, and deep belly breath. | L11: Seated dance moves on a chair with expressive arm rolls and seated foot taps. | M11: https://www.youtube.com/results?search_query=15+minute+beginner+bollywood+dance+workout+low+impact
A12: 2026-11-03 | B12: 11 | C12: Tuesday | D12: ZUMBA SESSION | E12: 15-Min Feel-Good Latin Zumba Party (Knee-Friendly, Low Impact) | F12: 15 | G12: 105 | H12: Latin Fiesta Dance | I12: 2 minutes easy hip circles and gentle arm sweeps. Gentle Latin rhythms (Merengue, Salsa, Bachata). Keep knees soft and absorb rhythm naturally. | J12: Merengue 6-Count March (4 mins) • Salsa Forward & Back Step (4 mins) • Reggaeton Gentle Bounce (3 mins) • Bachata Side Touch (4 mins) | K12: 3 minutes calm swaying and calf stretch. | L12: Chair-supported dance steps holding dining table or chair back. | M12: https://www.youtube.com/results?search_query=15+minute+easy+zumba+dance+workout+for+beginners+low+impact
A13: 2026-11-04 | B13: 12 | C13: Wednesday | D13: REST DAY | E13: REST DAY — Rest, Recover & Nourish ❤️ | F13: 0 | G13: 0 | H13: Restorative Rest | I13: Scheduled REST DAY (Wednesday) — Muscle recovery, sleep & nervous system rest. Zero workout pressure! ❤️ | J13: Zero workout assigned. Rest is 100% productive and honored. Keep hydration & comfortable meals. | K13: Hand on heart, deep peaceful breathing, soothing chamomile or warm water. | L13: Optional gentle stroll around room if desired, never mandatory. | M13: N/A (Scheduled Rest Day)
... A241: 2027-06-20 | B241: 240 | C241: Sunday | D241: REST DAY | E241: REST DAY — Rest, Recover & Nourish ❤️ | F241: 0 | G241: 0 | H241: Restorative Rest | I241: Scheduled REST DAY (Sunday) — Muscle recovery, sleep & nervous system rest. Zero workout pressure! ❤️ | J241: Zero workout assigned. Rest is 100% productive and honored. Keep hydration & comfortable meals. | K241: Hand on heart, deep peaceful breathing, soothing chamomile or warm water. | L241: Optional gentle stroll around room if desired, never mandatory. | M241: N/A (Scheduled Rest Day)

Sheet Actual Food Log
A1: Date | B1: Meal Category | C1: Food Item Name | D1: Quantity / Weight | E1: Calories (kcal) | F1: Protein (g) | G1: Carbs (g) | H1: Fat (g) | I1: From Plan? | J1: Notes
A2: 2026-10-24 | B2: Breakfast | C2: Steamed Idlis with Sambar & 1 Boiled Egg | D2: 2 idlis (100g) + sambar + 1 egg | E2: 260 | F2: 13 | G2: 34 | H2: 7 | I2: Yes | J2: Period Day 1 comfort breakfast
A3: 2026-10-24 | B3: Morning Snack | C3: Tender Coconut Water | D3: 1 glass (220ml) | E3: 45 | F3: 1 | G3: 10 | H3: 0 | I3: Yes | J3: Electrolyte cramp ease
A4: 2026-10-24 | B4: Lunch | C4: Sona Masoori Rice + Dal Sambar + Beans Palya | D4: 140g rice + 180g sambar + 100g beans | E4: 380 | F4: 12 | G4: 68 | H4: 6 | I4: Yes | J4: Comforting home meal
A5: 2026-10-24 | B5: Evening Snack | C5: Roasted Chana & Majjige | D5: 25g chana + 200ml buttermilk | E5: 135 | F5: 7 | G5: 16 | H5: 3 | I5: Yes | J5: Light snack
A6: 2026-10-24 | B6: Dinner | C6: 2 Whole Wheat Phulkas + Homestyle Chicken Curry | D6: 2 phulkas (75g) + 120g chicken curry | E6: 430 | F6: 29 | G6: 44 | H6: 13 | I6: Yes | J6: High protein dinner
A7: 2026-10-25 | B7: Breakfast | C7: Vegetable Poha with Peanuts & 1 Boiled Egg | D7: 160g poha + 1 egg | E7: 330 | F7: 13 | G7: 44 | H7: 11 | I7: Yes | J7: Day 2 breakfast
A8: 2026-10-25 | B8: Morning Snack | C8: Fresh Papaya slices | D8: 150g bowl | E8: 60 | F8: 1 | G8: 14 | H8: 0.2 | I8: Yes | J8: Sweet & refreshing
A9: 2026-10-25 | B9: Lunch | C9: 2 Soft Phulkas + Egg Curry + Cabbage Poriyal | D9: 2 phulkas + 2 eggs in curry + 120g poriyal | E9: 440 | F9: 22 | G9: 48 | H9: 16 | I9: Yes | J9: Balanced lunch
A10: 2026-10-25 | B10: Evening Snack | C10: Boiled Sweet Corn with Lemon | D10: 1 cup (120g) | E10: 120 | F10: 4 | G10: 24 | H10: 1.5 | I10: Yes | J10: Hot & tasty
A11: 2026-10-25 | B11: Dinner | C11: 2 Phulkas + Fresh Paneer Bhurji + Cucumber | D11: 2 phulkas + 90g paneer + 100g cucumber | E11: 445 | F11: 21 | G11: 44 | H11: 19 | I11: Yes | J11: Satisfying dinner
A12: 2026-10-26 | B12: Breakfast | C12: Rava Upma with Peanuts + 1 Boiled Egg | D12: 180g upma + 1 egg | E12: 340 | F12: 14 | G12: 44 | H12: 12 | I12: Yes | J12: Day 3 breakfast
A13: 2026-10-26 | B13: Morning Snack | C13: Spiced Buttermilk (Majjige) | D13: 220ml glass | E13: 45 | F13: 3 | G13: 4 | H13: 1.5 | I13: Yes | J13: Digestive cool
... A21: 2026-10-27 | B21: Dinner | C21: 2 Soft Phulkas + 2 Boiled Eggs in Tomato Curry | D21: 2 phulkas + 2 eggs in curry | E21: 415 | F21: 21 | G21: 42 | H21: 15 | I21: Yes | J21: Warm dinner

Sheet Actual Exercise Log
A1: Date | B1: Zumba / Movement Title | C1: Duration (Mins) | D1: Intensity / MET | E1: Estimated Calories Burned (kcal) | F1: Estimation Method | G1: Feeling & Notes
A2: 2026-10-24 | B2: Rest Day Honored ❤️ | C2: 0 | D2: 1 | E2: 0 | F2: Scheduled Rest Day | G2: Period Day 1 cramps; rested with warm herbal tea
A3: 2026-10-25 | B3: 12-Min Gentle Slow Dance & Pelvic Sway | C3: 12 | D3: 3.2 | E3: 55 | F3: MET 3.2 Restorative | G3: Gentle dance hip sway eased lower back stiffness
A4: 2026-10-26 | B4: 15-Min Joyful Beginner Bollywood Zumba | C4: 15 | D4: 4.8 | E4: 105 | F4: MET 4.8 Dance Equation | G4: Loved the upbeat music, smile on face throughout!
A5: 2026-10-27 | B5: 15-Min Feel-Good Latin Zumba Party | C5: 15 | D5: 4.8 | E5: 105 | F5: MET 4.8 Dance Equation | G5: Easy steps, no jumping, knee felt great

Sheet Daily Calorie Summary
A1: Date | B1: Day # | C1: Day of Week | D1: Actual Calories Consumed (kcal) | E1: Actual Protein Consumed (g) | F1: Estimated Zumba & Exercise Calories (kcal) | G1: Baseline Daily Expenditure (kcal) | H1: Estimated Total Daily Expenditure (TDEE) (kcal) | I1: Estimated Calorie Deficit / Surplus (kcal) | J1: Planned Calorie Target (kcal) | K1: Intake vs Target Variance (kcal) | L1: Scheduled Zumba / Rest | M1: Session Completed? | N1: Daily Notes
A2: 2026-10-24 | B2: 1 | C2: Saturday | D2: =IFERROR(SUMIFS('Actual Food Log'!E:E, 'Actual Food Log'!A:A, A2), 0) | E2: =IFERROR(SUMIFS('Actual Food Log'!F:F, 'Actual Food Log'!A:A, A2), 0) | F2: =IFERROR(SUMIFS('Actual Exercise Log'!E:E, 'Actual Exercise Log'!A:A, A2), 0) | G2: =Setup!$B$18 | H2: =IF(D2>0, G2 + F2, G2) | I2: =IF(D2>0, H2 - D2, 0) | J2: =Setup!$B$20 | K2: =IF(D2>0, D2 - J2, 0) | L2: REST DAY | M2: Rest Day Honored ❤️
A3: 2026-10-25 | B3: 2 | C3: Sunday | D3: =IFERROR(SUMIFS('Actual Food Log'!E:E, 'Actual Food Log'!A:A, A3), 0) | E3: =IFERROR(SUMIFS('Actual Food Log'!F:F, 'Actual Food Log'!A:A, A3), 0) | F3: =IFERROR(SUMIFS('Actual Exercise Log'!E:E, 'Actual Exercise Log'!A:A, A3), 0) | G3: =Setup!$B$18 | H3: =IF(D3>0, G3 + F3, G3) | I3: =IF(D3>0, H3 - D3, 0) | J3: =Setup!$B$20 | K3: =IF(D3>0, D3 - J3, 0) | L3: 12-Min Gentle Slow Dance & Pelvic Sway (Restorative Flow) | M3: Completed
A4: 2026-10-26 | B4: 3 | C4: Monday | D4: =IFERROR(SUMIFS('Actual Food Log'!E:E, 'Actual Food Log'!A:A, A4), 0) | E4: =IFERROR(SUMIFS('Actual Food Log'!F:F, 'Actual Food Log'!A:A, A4), 0) | F4: =IFERROR(SUMIFS('Actual Exercise Log'!E:E, 'Actual Exercise Log'!A:A, A4), 0) | G4: =Setup!$B$18 | H4: =IF(D4>0, G4 + F4, G4) | I4: =IF(D4>0, H4 - D4, 0) | J4: =Setup!$B$20 | K4: =IF(D4>0, D4 - J4, 0) | L4: 15-Min Joyful Beginner Bollywood Zumba Dance Party | M4: Completed
A5: 2026-10-27 | B5: 4 | C5: Tuesday | D5: =IFERROR(SUMIFS('Actual Food Log'!E:E, 'Actual Food Log'!A:A, A5), 0) | E5: =IFERROR(SUMIFS('Actual Food Log'!F:F, 'Actual Food Log'!A:A, A5), 0) | F5: =IFERROR(SUMIFS('Actual Exercise Log'!E:E, 'Actual Exercise Log'!A:A, A5), 0) | G5: =Setup!$B$18 | H5: =IF(D5>0, G5 + F5, G5) | I5: =IF(D5>0, H5 - D5, 0) | J5: =Setup!$B$20 | K5: =IF(D5>0, D5 - J5, 0) | L5: 15-Min Feel-Good Latin Zumba Party (Knee-Friendly, Low Impact) | M5: Completed
A6: 2026-10-28 | B6: 5 | C6: Wednesday | D6: =IFERROR(SUMIFS('Actual Food Log'!E:E, 'Actual Food Log'!A:A, A6), 0) | E6: =IFERROR(SUMIFS('Actual Food Log'!F:F, 'Actual Food Log'!A:A, A6), 0) | F6: =IFERROR(SUMIFS('Actual Exercise Log'!E:E, 'Actual Exercise Log'!A:A, A6), 0) | G6: =Setup!$B$18 | H6: =IF(D6>0, G6 + F6, G6) | I6: =IF(D6>0, H6 - D6, 0) | J6: =Setup!$B$20 | K6: =IF(D6>0, D6 - J6, 0) | L6: REST DAY | M6: Rest Day Honored ❤️
A7: 2026-10-29 | B7: 6 | C7: Thursday | D7: =IFERROR(SUMIFS('Actual Food Log'!E:E, 'Actual Food Log'!A:A, A7), 0) | E7: =IFERROR(SUMIFS('Actual Food Log'!F:F, 'Actual Food Log'!A:A, A7), 0) | F7: =IFERROR(SUMIFS('Actual Exercise Log'!E:E, 'Actual Exercise Log'!A:A, A7), 0) | G7: =Setup!$B$18 | H7: =IF(D7>0, G7 + F7, G7) | I7: =IF(D7>0, H7 - D7, 0) | J7: =Setup!$B$20 | K7: =IF(D7>0, D7 - J7, 0) | L7: 15-Min Joyful Beginner Bollywood Zumba Dance Party | M7: Pending
A8: 2026-10-30 | B8: 7 | C8: Friday | D8: =IFERROR(SUMIFS('Actual Food Log'!E:E, 'Actual Food Log'!A:A, A8), 0) | E8: =IFERROR(SUMIFS('Actual Food Log'!F:F, 'Actual Food Log'!A:A, A8), 0) | F8: =IFERROR(SUMIFS('Actual Exercise Log'!E:E, 'Actual Exercise Log'!A:A, A8), 0) | G8: =Setup!$B$18 | H8: =IF(D8>0, G8 + F8, G8) | I8: =IF(D8>0, H8 - D8, 0) | J8: =Setup!$B$20 | K8: =IF(D8>0, D8 - J8, 0) | L8: 15-Min Feel-Good Latin Zumba Party (Knee-Friendly, Low Impact) | M8: Pending
A9: 2026-10-31 | B9: 8 | C9: Saturday | D9: =IFERROR(SUMIFS('Actual Food Log'!E:E, 'Actual Food Log'!A:A, A9), 0) | E9: =IFERROR(SUMIFS('Actual Food Log'!F:F, 'Actual Food Log'!A:A, A9), 0) | F9: =IFERROR(SUMIFS('Actual Exercise Log'!E:E, 'Actual Exercise Log'!A:A, A9), 0) | G9: =Setup!$B$18 | H9: =IF(D9>0, G9 + F9, G9) | I9: =IF(D9>0, H9 - D9, 0) | J9: =Setup!$B$20 | K9: =IF(D9>0, D9 - J9, 0) | L9: REST DAY | M9: Rest Day Honored ❤️
A10: 2026-11-01 | B10: 9 | C10: Sunday | D10: =IFERROR(SUMIFS('Actual Food Log'!E:E, 'Actual Food Log'!A:A, A10), 0) | E10: =IFERROR(SUMIFS('Actual Food Log'!F:F, 'Actual Food Log'!A:A, A10), 0) | F10: =IFERROR(SUMIFS('Actual Exercise Log'!E:E, 'Actual Exercise Log'!A:A, A10), 0) | G10: =Setup!$B$18 | H10: =IF(D10>0, G10 + F10, G10) | I10: =IF(D10>0, H10 - D10, 0) | J10: =Setup!$B$20 | K10: =IF(D10>0, D10 - J10, 0) | L10: REST DAY | M10: Rest Day Honored ❤️
A11: 2026-11-02 | B11: 10 | C11: Monday | D11: =IFERROR(SUMIFS('Actual Food Log'!E:E, 'Actual Food Log'!A:A, A11), 0) | E11: =IFERROR(SUMIFS('Actual Food Log'!F:F, 'Actual Food Log'!A:A, A11), 0) | F11: =IFERROR(SUMIFS('Actual Exercise Log'!E:E, 'Actual Exercise Log'!A:A, A11), 0) | G11: =Setup!$B$18 | H11: =IF(D11>0, G11 + F11, G11) | I11: =IF(D11>0, H11 - D11, 0) | J11: =Setup!$B$20 | K11: =IF(D11>0, D11 - J11, 0) | L11: 15-Min Joyful Beginner Bollywood Zumba Dance Party | M11: Pending
A12: 2026-11-03 | B12: 11 | C12: Tuesday | D12: =IFERROR(SUMIFS('Actual Food Log'!E:E, 'Actual Food Log'!A:A, A12), 0) | E12: =IFERROR(SUMIFS('Actual Food Log'!F:F, 'Actual Food Log'!A:A, A12), 0) | F12: =IFERROR(SUMIFS('Actual Exercise Log'!E:E, 'Actual Exercise Log'!A:A, A12), 0) | G12: =Setup!$B$18 | H12: =IF(D12>0, G12 + F12, G12) | I12: =IF(D12>0, H12 - D12, 0) | J12: =Setup!$B$20 | K12: =IF(D12>0, D12 - J12, 0) | L12: 15-Min Feel-Good Latin Zumba Party (Knee-Friendly, Low Impact) | M12: Pending
A13: 2026-11-04 | B13: 12 | C13: Wednesday | D13: =IFERROR(SUMIFS('Actual Food Log'!E:E, 'Actual Food Log'!A:A, A13), 0) | E13: =IFERROR(SUMIFS('Actual Food Log'!F:F, 'Actual Food Log'!A:A, A13), 0) | F13: =IFERROR(SUMIFS('Actual Exercise Log'!E:E, 'Actual Exercise Log'!A:A, A13), 0) | G13: =Setup!$B$18 | H13: =IF(D13>0, G13 + F13, G13) | I13: =IF(D13>0, H13 - D13, 0) | J13: =Setup!$B$20 | K13: =IF(D13>0, D13 - J13, 0) | L13: REST DAY | M13: Rest Day Honored ❤️
... A241: 2027-06-20 | B241: 240 | C241: Sunday | D241: =IFERROR(SUMIFS('Actual Food Log'!E:E, 'Actual Food Log'!A:A, A241), 0) | E241: =IFERROR(SUMIFS('Actual Food Log'!F:F, 'Actual Food Log'!A:A, A241), 0) | F241: =IFERROR(SUMIFS('Actual Exercise Log'!E:E, 'Actual Exercise Log'!A:A, A241), 0) | G241: =Setup!$B$18 | H241: =IF(D241>0, G241 + F241, G241) | I241: =IF(D241>0, H241 - D241, 0) | J241: =Setup!$B$20 | K241: =IF(D241>0, D241 - J241, 0) | L241: REST DAY | M241: Rest Day Honored ❤️

Sheet Weight & Measurements
A1: Date | B1: Day # | C1: Day of Week | D1: Morning Weight (kg) | E1: Weekly Rolling Average (kg) | F1: Weight Change from Baseline (kg) | G1: Waist Measurement (inches) | H1: Menstrual / Cycle Phase | I1: Notes & Non-Scale Victories
A2: 2026-10-24 | B2: 1 | C2: Saturday | D2: 88.5 | E2: =IF(D2<>"", ROUND(AVERAGE(D2:D2), 2), "") | F2: =IF(D2<>"", ROUND(D2 - Setup!$B$6, 2), "") | H2: Menstrual Day 1 | I2: Starting baseline check-in (88.5 kg). Day 1 period water retention.
A3: 2026-10-25 | B3: 2 | C3: Sunday | D3: 86.2 | E3: =IF(D3<>"", ROUND(AVERAGE(D2:D3), 2), "") | F3: =IF(D3<>"", ROUND(D3 - Setup!$B$6, 2), "") | H3: Menstrual Day 2 | I3: Current updated weight check-in (86.2 kg). Sustainable progress ❤️
A4: 2026-10-26 | B4: 3 | C4: Monday | D4: 86.2 | E4: =IF(D4<>"", ROUND(AVERAGE(D2:D4), 2), "") | F4: =IF(D4<>"", ROUND(D4 - Setup!$B$6, 2), "") | H4: Menstrual Day 3
A5: 2026-10-27 | B5: 4 | C5: Tuesday | D5: 86.1 | E5: =IF(D5<>"", ROUND(AVERAGE(D2:D5), 2), "") | F5: =IF(D5<>"", ROUND(D5 - Setup!$B$6, 2), "") | H5: Menstrual Day 4 | I5: Feeling lighter, energized after Bollywood Zumba
A6: 2026-10-28 | B6: 5 | C6: Wednesday | E6: =IF(D6<>"", ROUND(AVERAGE(D2:D6), 2), "") | F6: =IF(D6<>"", ROUND(D6 - Setup!$B$6, 2), "") | H6: Follicular Phase
A7: 2026-10-29 | B7: 6 | C7: Thursday | E7: =IF(D7<>"", ROUND(AVERAGE(D2:D7), 2), "") | F7: =IF(D7<>"", ROUND(D7 - Setup!$B$6, 2), "") | H7: Follicular Phase
A8: 2026-10-30 | B8: 7 | C8: Friday | E8: =IF(D8<>"", ROUND(AVERAGE(D2:D8), 2), "") | F8: =IF(D8<>"", ROUND(D8 - Setup!$B$6, 2), "") | H8: Follicular Phase
A9: 2026-10-31 | B9: 8 | C9: Saturday | E9: =IF(D9<>"", ROUND(AVERAGE(D3:D9), 2), "") | F9: =IF(D9<>"", ROUND(D9 - Setup!$B$6, 2), "") | H9: Follicular Phase
A10: 2026-11-01 | B10: 9 | C10: Sunday | E10: =IF(D10<>"", ROUND(AVERAGE(D4:D10), 2), "") | F10: =IF(D10<>"", ROUND(D10 - Setup!$B$6, 2), "") | H10: Follicular Phase
A11: 2026-11-02 | B11: 10 | C11: Monday | E11: =IF(D11<>"", ROUND(AVERAGE(D5:D11), 2), "") | F11: =IF(D11<>"", ROUND(D11 - Setup!$B$6, 2), "") | H11: Follicular Phase
A12: 2026-11-03 | B12: 11 | C12: Tuesday | E12: =IF(D12<>"", ROUND(AVERAGE(D6:D12), 2), "") | F12: =IF(D12<>"", ROUND(D12 - Setup!$B$6, 2), "") | H12: Follicular Phase
A13: 2026-11-04 | B13: 12 | C13: Wednesday | E13: =IF(D13<>"", ROUND(AVERAGE(D7:D13), 2), "") | F13: =IF(D13<>"", ROUND(D13 - Setup!$B$6, 2), "") | H13: Follicular Phase
A14: 2026-11-05 | B14: 13 | C14: Thursday | E14: =IF(D14<>"", ROUND(AVERAGE(D8:D14), 2), "") | F14: =IF(D14<>"", ROUND(D14 - Setup!$B$6, 2), "") | H14: Follicular Phase
A15: 2026-11-06 | B15: 14 | C15: Friday | E15: =IF(D15<>"", ROUND(AVERAGE(D9:D15), 2), "") | F15: =IF(D15<>"", ROUND(D15 - Setup!$B$6, 2), "") | H15: Follicular Phase
A16: 2026-11-07 | B16: 15 | C16: Saturday | E16: =IF(D16<>"", ROUND(AVERAGE(D10:D16), 2), "") | F16: =IF(D16<>"", ROUND(D16 - Setup!$B$6, 2), "") | H16: Follicular Phase
A17: 2026-11-08 | B17: 16 | C17: Sunday | E17: =IF(D17<>"", ROUND(AVERAGE(D11:D17), 2), "") | F17: =IF(D17<>"", ROUND(D17 - Setup!$B$6, 2), "") | H17: Follicular Phase
A18: 2026-11-09 | B18: 17 | C18: Monday | E18: =IF(D18<>"", ROUND(AVERAGE(D12:D18), 2), "") | F18: =IF(D18<>"", ROUND(D18 - Setup!$B$6, 2), "") | H18: Follicular Phase
A19: 2026-11-10 | B19: 18 | C19: Tuesday | E19: =IF(D19<>"", ROUND(AVERAGE(D13:D19), 2), "") | F19: =IF(D19<>"", ROUND(D19 - Setup!$B$6, 2), "") | H19: Follicular Phase
... A241: 2027-06-20 | B241: 240 | C241: Sunday | E241: =IF(D241<>"", ROUND(AVERAGE(D235:D241), 2), "") | F241: =IF(D241<>"", ROUND(D241 - Setup!$B$6, 2), "") | H241: Follicular Phase

Sheet Grocery List
A1: HER JOURNEY 240 — AFFORDABLE BENGALURU GROCERY LIST
A2: Item Name | B2: Kannada / Regional Name | C2: Category | D2: Typical Purchase Qty | E2: Approx Price (₹) | F2: Purchase Frequency
A3: Sona Masoori Rice | B3: ಅಕ್ಕಿ (Akki) | C3: Grains & Millets | D3: 5 kg bag | E3: 320 | F3: Monthly
A4: Whole Wheat Flour (Atta) | B4: ಗೋಧಿ ಹಿಟ್ಟು (Godhi Hittu) | C4: Grains & Millets | D4: 2 kg bag | E4: 110 | F4: Bi-weekly
A5: Ragi Flour (Finger Millet) | B5: ರಾಗಿ ಹಿಟ್ಟು (Ragi Hittu) | C5: Grains & Millets | D5: 1 kg bag | E5: 60 | F5: Monthly
A6: Rolled Oats | B6: ಓಟ್ಸ್ (Oats) | C6: Grains & Millets | D6: 1 kg bag | E6: 175 | F6: Monthly
A7: Roasted Rava / Semolina | B7: ರವೆ (Rave) | C7: Grains & Millets | D7: 1 kg packet | E7: 65 | F7: Monthly
A8: Thick Poha (Flattened Rice) | B8: ಅವಲಕ್ಕಿ (Avalakki) | C8: Grains & Millets | D8: 1 kg packet | E8: 65 | F8: Monthly
A9: Toor Dal | B9: ತೊಗರಿ ಬೇಳೆ (Togari Bele) | C9: Dals & Pulses | D9: 1 kg bag | E9: 160 | F9: Monthly
A10: Moong Dal | B10: ಹೆಸರು ಬೇಳೆ (Hesaru Bele) | C10: Dals & Pulses | D10: 500g | E10: 85 | F10: Monthly
A11: Chana Dal | B11: ಕಡಲೆ ಬೇಳೆ (Kadale Bele) | C11: Dals & Pulses | D11: 500g | E11: 70 | F11: Monthly
A12: Sprouted Green Moong | B12: ಮೊಳಕೆ ಕಾಳು (Molake Kaalu) | C12: Dals & Pulses | D12: 500g | E12: 75 | F12: Weekly
A13: Kabuli Chana (Chickpeas) | B13: ಕಡಲೆ ಕಾಳು (Kadale Kaalu) | C13: Dals & Pulses | D13: 500g | E13: 70 | F13: Monthly
A14: Roasted Chana / Puri Kadale | B14: ಹುರಿಗಡಲೆ (Hurigadale) | C14: Snacks & Proteins | D14: 500g packet | E14: 65 | F14: Monthly
... A30: Raw Almonds (Badam) | B30: ಬಾದಾಮಿ (Badami) | C30: Healthy Fats | D30: 250g packet | E30: 220 | F30: Monthly

Sheet Dashboard
A1: HER JOURNEY 240 — PROGRESS & ZUMBA ADHERENCE DASHBOARD
A3: TOTAL JOURNEY 240 Days Oct 24, 2026 – Jun 20, 2027 | C3: BASELINE WEIGHT 88.5 kg October 24, 2026 | E3: CURRENT WEIGHT 86.2 kg Progress: -2.3 kg reduction ❤️ | G3: DAILY MOVEMENT Joyful Zumba 15–20 mins • Fun Bollywood & Latin
